{
    "parent": "item/generated",
    "textures": {
        "layer0": "minewatch:items/zenyatta_weapon"
    },
	"display": {
		 "thirdperson_righthand": {
            "rotation": [ 70, -90, 0 ],
			"translation": [ 0, 0, 0 ],
			"scale": [ 0.3, 0.3, 0.3 ]
        },
        "thirdperson_lefthand": {
			"rotation": [ 70, 90, 0 ],
			"translation": [ 0, 0, 0 ],
			"scale": [ 0.3, 0.3, 0.3 ]
        },
		 "firstperson_righthand": {
            "rotation": [ 0, -90, 0 ],
            "translation": [ 2, 5.2, 0],
            "scale": [ 0.3, 0.3, 0.3 ]
        },
        "firstperson_lefthand": {
            "rotation": [ 0, 90, 0 ],
            "translation": [ 2, 5.2, 0],
            "scale": [ 0.3, 0.3, 0.3 ]
        },
        "fixed": {
            "scale": [ 0.3, 0.3, 0.3 ]
        }
	}
}
